MANIFEST.in
README.txt
setup.cfg
setup.py
collective/__init__.py
collective.cdn.core.egg-info/PKG-INFO
collective.cdn.core.egg-info/SOURCES.txt
collective.cdn.core.egg-info/dependency_links.txt
collective.cdn.core.egg-info/entry_points.txt
collective.cdn.core.egg-info/namespace_packages.txt
collective.cdn.core.egg-info/not-zip-safe
collective.cdn.core.egg-info/requires.txt
collective.cdn.core.egg-info/top_level.txt
collective/cdn/__init__.py
collective/cdn/core/README.txt
collective/cdn/core/__init__.py
collective/cdn/core/config.py
collective/cdn/core/configure.zcml
collective/cdn/core/image.py
collective/cdn/core/setuphandlers.py
collective/cdn/core/testing.py
collective/cdn/core/utils.py
collective/cdn/core/version.txt
collective/cdn/core/vocabularies.py
collective/cdn/core/browser/__init__.py
collective/cdn/core/browser/base.py
collective/cdn/core/browser/configure.zcml
collective/cdn/core/browser/interfaces.py
collective/cdn/core/browser/kss.py
collective/cdn/core/browser/scripts.py
collective/cdn/core/browser/styles.py
collective/cdn/core/browser/resources/cdn_icon.png
collective/cdn/core/controlpanel/__init__.py
collective/cdn/core/controlpanel/cdn.py
collective/cdn/core/controlpanel/configure.zcml
collective/cdn/core/docs/__init__.py
collective/cdn/core/docs/browser.txt
collective/cdn/core/interfaces/__init__.py
collective/cdn/core/interfaces/provider.py
collective/cdn/core/locales/collective.cdn.core.pot
collective/cdn/core/locales/manual.pot
collective/cdn/core/locales/rebuildAll.sh
collective/cdn/core/locales/pt_BR/LC_MESSAGES/collective.cdn.core.mo
collective/cdn/core/locales/pt_BR/LC_MESSAGES/collective.cdn.core.po
collective/cdn/core/profiles/default/browserlayer.xml
collective/cdn/core/profiles/default/collective.cdn.core.txt
collective/cdn/core/profiles/default/controlpanel.xml
collective/cdn/core/profiles/default/import_steps.xml
collective/cdn/core/profiles/default/metadata.xml
collective/cdn/core/profiles/default/propertiestool.xml
collective/cdn/core/tests/__init__.py
collective/cdn/core/tests/provider.py
collective/cdn/core/tests/test.gif
collective/cdn/core/tests/test_functional.py
collective/cdn/core/tests/test_image.py
collective/cdn/core/tests/testing.zcml
collective/cdn/core/upgrades/__init__.py
collective/cdn/core/upgrades/configure.zcml
collective/cdn/core/upgrades/to01.py
